[
  {
    "name": "Paulin",
    "link": "#"
  },
  {
    "name": "Unixiea",
    "link": "#"
  },
  {
    "name": "Muela",
    "link": "#"
  },
  {
    "name": "Terri",
    "link": "#"
  },
  {
    "name": "Diam",
    "link": "#"
  },
  {
    "name": "Lenerin",
    "link": "#"
  },
  {
    "name": "Fifiachlo",
    "link": "#"
  },
  {
    "name": "Zara",
    "link": "#"
  },
  {
    "name": "Veyony",
    "link": "#"
  },
  {
    "name": "Rrickya",
    "link": "#"
  },
  {
    "name": "Harondrag",
    "link": "#"
  },
  {
    "name": "Jadel",
    "link": "#"
  },
  {
    "name": "Ganil",
    "link": "#"
  },
  {
    "name": "Wilesl",
    "link": "#"
  },
  {
    "name": "Jaegardi",
    "link": "#"
  },
  {
    "name": "Ossi",
    "link": "#"
  },
  {
    "name": "Pster",
    "link": "#"
  },
  {
    "name": "Lathleen",
    "link": "#"
  },
  {
    "name": "Rcelleralp",
    "link": "#"
  },
  {
    "name": "Sperstep",
    "link": "#"
  },
  {
    "name": "Nrieldo",
    "link": "#"
  },
  {
    "name": "Blit",
    "link": "#"
  },
  {
    "name": "Gnieveri",
    "link": "#"
  },
  {
    "name": "Lvini",
    "link": "#"
  },
  {
    "name": "Janev",
    "link": "#"
  },
  {
    "name": "Selies",
    "link": "#"
  },
  {
    "name": "Bdulcin",
    "link": "#"
  }
]